waapi/__init__.py
waapi/client/__init__.py
waapi/client/client.py
waapi/client/event.py
waapi/client/executor.py
waapi/client/interface.py
waapi/wamp/__init__.py
waapi/wamp/ak_autobahn.py
waapi/wamp/async_compatibility.py
waapi/wamp/async_decoupled_client.py
waapi/wamp/interface.py
waapi_client-0.8.1.dist-info/licenses/LICENSE
waapi_client-0.8.1.dist-info/METADATA
waapi_client-0.8.1.dist-info/WHEEL
waapi_client-0.8.1.dist-info/top_level.txt
waapi_client-0.8.1.dist-info/RECORD
