Metadata-Version: 2.4
Name: waapi-client
Version: 0.8.1
Summary: Wwise Authoring API client.
Author: Audiokinetic
Author-email: Samuel Longchamps <slongchamps@audiokinetic.com>
Maintainer-email: Samuel Longchamps <slongchamps@audiokinetic.com>
License-Expression: Apache-2.0
Project-URL: Homepage, https://github.com/audiokinetic/waapi-client-python
Project-URL: Issues, https://github.com/audiokinetic/waapi-client-python/issues
Project-URL: Documentation, https://www.audiokinetic.com/library/edge/?source=SDK&id=waapi_index.html
Project-URL: Releases, https://github.com/audiokinetic/waapi-client-python/releases
Keywords: waapi,wwise,audiokinetic
Classifier: Intended Audience :: Developers
Classifier: Programming Language :: Python :: 3 :: Only
Classifier: Topic :: Software Development :: Libraries :: Python Modules
Classifier: Development Status :: 4 - Beta
Classifier: Operating System :: Microsoft :: Windows
Classifier: Operating System :: MacOS :: MacOS X
Classifier: Operating System :: POSIX :: Linux
Requires-Python: >=3.10
License-File: LICENSE
Requires-Dist: autobahn==24.4.2
Dynamic: license-file
